pyptv3/__init__.py
pyptv3/access_denied_error.py
pyptv3/async_client.py
pyptv3/client.py
pyptv3/departures.py
pyptv3/directions.py
pyptv3/disruptions.py
pyptv3/invalid_request_error.py
pyptv3/not_found_error.py
pyptv3/outlets.py
pyptv3/patterns.py
pyptv3/query_params.py
pyptv3/route_types.py
pyptv3/routes.py
pyptv3/runs.py
pyptv3/search.py
pyptv3/stops.py
pyptv3/unknown_error.py
pyptv3/url_builder.py
pyptv3-0.0.4.dist-info/METADATA
pyptv3-0.0.4.dist-info/RECORD
pyptv3-0.0.4.dist-info/WHEEL
pyptv3-0.0.4.dist-info/top_level.txt
