Metadata-Version: 2.1
Name: pyptv3
Version: 0.0.4
Summary: Access the Public Transport Victoria API with Python 3
Home-page: https://github.com/madpilot/pyptv3
Author: Myles Eftos
Author-email: myles@madpilot.com.au
License: UNKNOWN
Platform: UNKNOWN
Classifier: Programming Language :: Python :: 3
Classifier: License :: OSI Approved :: MIT License
Classifier: Operating System :: OS Independent
